[
    {
      "inputs": [
        {
          "internalType": "address",
          "name": "_putsPool",
          "type": "address"
        },
        {
          "internalType": "address",
          "name": "_errorController",
          "type": "address"
        }
      ],
      "stateMutability": "nonpayable",
      "type": "constructor"
    },
    {
      "anonymous": false,
      "inputs": [
        {
          "indexed": false,
          "internalType": "uint256",
          "name": "epoch",
          "type": "uint256"
        },
        {
          "indexed": false,
          "internalType": "uint256",
          "name": "maxStrike",
          "type": "uint256"
        },
        {
          "indexed": false,
          "internalType": "uint256",
          "name": "startTime",
          "type": "uint256"
        },
        {
          "indexed": false,
          "internalType": "uint256",
          "name": "index",
          "type": "uint256"
        }
      ],
      "name": "NewCheckpoint",
      "type": "event"
    },
    {
      "anonymous": false,
      "inputs": [
        {
          "indexed": false,
          "internalType": "uint256",
          "name": "epoch",
          "type": "uint256"
        },
        {
          "indexed": false,
          "internalType": "uint256",
          "name": "strike",
          "type": "uint256"
        },
        {
          "indexed": true,
          "internalType": "address",
          "name": "user",
          "type": "address"
        },
        {
          "indexed": false,
          "internalType": "uint256",
          "name": "amount",
          "type": "uint256"
        },
        {
          "indexed": false,
          "internalType": "uint256",
          "name": "pnl",
          "type": "uint256"
        }
      ],
      "name": "NewSettle",
      "type": "event"
    },
    {
      "anonymous": false,
      "inputs": [
        {
          "indexed": true,
          "internalType": "uint256",
          "name": "epoch",
          "type": "uint256"
        },
        {
          "indexed": true,
          "internalType": "uint256",
          "name": "strike",
          "type": "uint256"
        },
        {
          "indexed": false,
          "internalType": "uint256",
          "name": "totalCollateral",
          "type": "uint256"
        },
        {
          "indexed": false,
          "internalType": "address",
          "name": "caller",
          "type": "address"
        }
      ],
      "name": "RelockCollateral",
      "type": "event"
    },
    {
      "anonymous": false,
      "inputs": [
        {
          "indexed": false,
          "internalType": "uint256",
          "name": "epoch",
          "type": "uint256"
        },
        {
          "indexed": false,
          "internalType": "uint256",
          "name": "totalCollateral",
          "type": "uint256"
        },
        {
          "indexed": false,
          "internalType": "address",
          "name": "caller",
          "type": "address"
        }
      ],
      "name": "UnlockCollateral",
      "type": "event"
    },
    {
      "anonymous": false,
      "inputs": [
        {
          "indexed": false,
          "internalType": "uint256",
          "name": "epoch",
          "type": "uint256"
        },
        {
          "indexed": false,
          "internalType": "uint256",
          "name": "strike",
          "type": "uint256"
        },
        {
          "indexed": false,
          "internalType": "uint256",
          "name": "amount",
          "type": "uint256"
        },
        {
          "indexed": false,
          "internalType": "address",
          "name": "caller",
          "type": "address"
        }
      ],
      "name": "Unwind",
      "type": "event"
    },
    {
      "inputs": [
        {
          "internalType": "uint256",
          "name": "_strike",
          "type": "uint256"
        },
        {
          "internalType": "uint256",
          "name": "_epoch",
          "type": "uint256"
        }
      ],
      "name": "addMaxStrike",
      "outputs": [],
      "stateMutability": "nonpayable",
      "type": "function"
    },
    {
      "inputs": [
        {
          "internalType": "uint256",
          "name": "price",
          "type": "uint256"
        },
        {
          "internalType": "uint256",
          "name": "strike",
          "type": "uint256"
        },
        {
          "internalType": "uint256",
          "name": "amount",
          "type": "uint256"
        }
      ],
      "name": "calculatePnl",
      "outputs": [
        {
          "internalType": "uint256",
          "name": "",
          "type": "uint256"
        }
      ],
      "stateMutability": "pure",
      "type": "function"
    },
    {
      "inputs": [
        {
          "internalType": "uint256",
          "name": "epoch",
          "type": "uint256"
        },
        {
          "internalType": "uint256",
          "name": "maxStrike",
          "type": "uint256"
        },
        {
          "internalType": "uint256",
          "name": "liquidity",
          "type": "uint256"
        }
      ],
      "name": "checkpoint",
      "outputs": [
        {
          "internalType": "uint256",
          "name": "index",
          "type": "uint256"
        }
      ],
      "stateMutability": "nonpayable",
      "type": "function"
    },
    {
      "inputs": [
        {
          "internalType": "uint256",
          "name": "",
          "type": "uint256"
        },
        {
          "internalType": "uint256",
          "name": "",
          "type": "uint256"
        }
      ],
      "name": "epochMaxStrikeCheckpointStartIndex",
      "outputs": [
        {
          "internalType": "uint256",
          "name": "",
          "type": "uint256"
        }
      ],
      "stateMutability": "view",
      "type": "function"
    },
    {
      "inputs": [
        {
          "internalType": "uint256",
          "name": "",
          "type": "uint256"
        },
        {
          "internalType": "uint256",
          "name": "",
          "type": "uint256"
        },
        {
          "internalType": "uint256",
          "name": "",
          "type": "uint256"
        }
      ],
      "name": "epochMaxStrikeCheckpoints",
      "outputs": [
        {
          "internalType": "uint256",
          "name": "startTime",
          "type": "uint256"
        },
        {
          "internalType": "uint256",
          "name": "totalLiquidity",
          "type": "uint256"
        },
        {
          "internalType": "uint256",
          "name": "totalLiquidityBalance",
          "type": "uint256"
        },
        {
          "internalType": "uint256",
          "name": "activeCollateral",
          "type": "uint256"
        },
        {
          "internalType": "uint256",
          "name": "unlockedCollateral",
          "type": "uint256"
        },
        {
          "internalType": "uint256",
          "name": "premiumAccrued",
          "type": "uint256"
        },
        {
          "internalType": "uint256",
          "name": "fundingAccrued",
          "type": "uint256"
        },
        {
          "internalType": "uint256",
          "name": "underlyingAccrued",
          "type": "uint256"
        }
      ],
      "stateMutability": "view",
      "type": "function"
    },
    {
      "inputs": [
        {
          "internalType": "uint256",
          "name": "_epoch",
          "type": "uint256"
        },
        {
          "internalType": "uint256",
          "name": "_maxStrike",
          "type": "uint256"
        },
        {
          "internalType": "uint256",
          "name": "_checkpoint",
          "type": "uint256"
        }
      ],
      "name": "getEpochMaxStrikeCheckpoint",
      "outputs": [
        {
          "components": [
            {
              "internalType": "uint256",
              "name": "startTime",
              "type": "uint256"
            },
            {
              "internalType": "uint256",
              "name": "totalLiquidity",
              "type": "uint256"
            },
            {
              "internalType": "uint256",
              "name": "totalLiquidityBalance",
              "type": "uint256"
            },
            {
              "internalType": "uint256",
              "name": "activeCollateral",
              "type": "uint256"
            },
            {
              "internalType": "uint256",
              "name": "unlockedCollateral",
              "type": "uint256"
            },
            {
              "internalType": "uint256",
              "name": "premiumAccrued",
              "type": "uint256"
            },
            {
              "internalType": "uint256",
              "name": "fundingAccrued",
              "type": "uint256"
            },
            {
              "internalType": "uint256",
              "name": "underlyingAccrued",
              "type": "uint256"
            }
          ],
          "internalType": "struct EpochMaxStrikeCheckpoint",
          "name": "",
          "type": "tuple"
        }
      ],
      "stateMutability": "view",
      "type": "function"
    },
    {
      "inputs": [
        {
          "internalType": "uint256",
          "name": "epoch",
          "type": "uint256"
        },
        {
          "internalType": "uint256",
          "name": "maxStrike",
          "type": "uint256"
        }
      ],
      "name": "getEpochMaxStrikeCheckpoints",
      "outputs": [
        {
          "components": [
            {
              "internalType": "uint256",
              "name": "startTime",
              "type": "uint256"
            },
            {
              "internalType": "uint256",
              "name": "totalLiquidity",
              "type": "uint256"
            },
            {
              "internalType": "uint256",
              "name": "totalLiquidityBalance",
              "type": "uint256"
            },
            {
              "internalType": "uint256",
              "name": "activeCollateral",
              "type": "uint256"
            },
            {
              "internalType": "uint256",
              "name": "unlockedCollateral",
              "type": "uint256"
            },
            {
              "internalType": "uint256",
              "name": "premiumAccrued",
              "type": "uint256"
            },
            {
              "internalType": "uint256",
              "name": "fundingAccrued",
              "type": "uint256"
            },
            {
              "internalType": "uint256",
              "name": "underlyingAccrued",
              "type": "uint256"
            }
          ],
          "internalType": "struct EpochMaxStrikeCheckpoint[]",
          "name": "checkpoints",
          "type": "tuple[]"
        }
      ],
      "stateMutability": "view",
      "type": "function"
    },
    {
      "inputs": [
        {
          "internalType": "uint256",
          "name": "epoch",
          "type": "uint256"
        }
      ],
      "name": "getEpochMaxStrikes",
      "outputs": [
        {
          "internalType": "uint256[]",
          "name": "maxStrikes",
          "type": "uint256[]"
        }
      ],
      "stateMutability": "view",
      "type": "function"
    },
    {
      "inputs": [
        {
          "internalType": "uint256",
          "name": "epoch",
          "type": "uint256"
        }
      ],
      "name": "getEpochMaxStrikesCollaterals",
      "outputs": [
        {
          "components": [
            {
              "internalType": "address",
              "name": "user",
              "type": "address"
            },
            {
              "internalType": "uint256",
              "name": "optionStrike",
              "type": "uint256"
            },
            {
              "internalType": "uint256",
              "name": "optionsAmount",
              "type": "uint256"
            },
            {
              "internalType": "uint256",
              "name": "index",
              "type": "uint256"
            },
            {
              "components": [
                {
                  "internalType": "uint256",
                  "name": "fundingRate",
                  "type": "uint256"
                },
                {
                  "internalType": "uint256",
                  "name": "expiryDelta",
                  "type": "uint256"
                },
                {
                  "internalType": "uint256",
                  "name": "collateralAccess",
                  "type": "uint256"
                }
              ],
              "internalType": "struct CollateralUnlock",
              "name": "collateralUnlock",
              "type": "tuple"
            }
          ],
          "internalType": "struct MaxStrikesCollateral[]",
          "name": "result",
          "type": "tuple[]"
        }
      ],
      "stateMutability": "view",
      "type": "function"
    },
    {
      "inputs": [
        {
          "internalType": "uint256",
          "name": "epoch",
          "type": "uint256"
        },
        {
          "internalType": "uint256",
          "name": "usersMaxStrikeCollateralIndex",
          "type": "uint256"
        },
        {
          "internalType": "address",
          "name": "user",
          "type": "address"
        }
      ],
      "name": "getEpochUserMaxStrikeWeights",
      "outputs": [
        {
          "components": [
            {
              "internalType": "uint256[]",
              "name": "maxStrikes",
              "type": "uint256[]"
            },
            {
              "internalType": "uint256[]",
              "name": "checkpoints",
              "type": "uint256[]"
            },
            {
              "internalType": "uint256[]",
              "name": "weights",
              "type": "uint256[]"
            }
          ],
          "internalType": "struct MaxStrikeWeights",
          "name": "result",
          "type": "tuple"
        }
      ],
      "stateMutability": "view",
      "type": "function"
    },
    {
      "inputs": [
        {
          "internalType": "address",
          "name": "user",
          "type": "address"
        },
        {
          "internalType": "uint256",
          "name": "epoch",
          "type": "uint256"
        }
      ],
      "name": "getUserMaxStrikesCollaterals",
      "outputs": [
        {
          "components": [
            {
              "internalType": "address",
              "name": "user",
              "type": "address"
            },
            {
              "internalType": "uint256",
              "name": "optionStrike",
              "type": "uint256"
            },
            {
              "internalType": "uint256",
              "name": "optionsAmount",
              "type": "uint256"
            },
            {
              "internalType": "uint256",
              "name": "index",
              "type": "uint256"
            },
            {
              "components": [
                {
                  "internalType": "uint256",
                  "name": "fundingRate",
                  "type": "uint256"
                },
                {
                  "internalType": "uint256",
                  "name": "expiryDelta",
                  "type": "uint256"
                },
                {
                  "internalType": "uint256",
                  "name": "collateralAccess",
                  "type": "uint256"
                }
              ],
              "internalType": "struct CollateralUnlock",
              "name": "collateralUnlock",
              "type": "tuple"
            }
          ],
          "internalType": "struct MaxStrikesCollateral[]",
          "name": "result",
          "type": "tuple[]"
        }
      ],
      "stateMutability": "view",
      "type": "function"
    },
    {
      "inputs": [
        {
          "internalType": "uint256",
          "name": "maxStrike",
          "type": "uint256"
        },
        {
          "internalType": "uint256",
          "name": "epoch",
          "type": "uint256"
        },
        {
          "internalType": "address",
          "name": "user",
          "type": "address"
        }
      ],
      "name": "getWithdrawAmounts",
      "outputs": [
        {
          "internalType": "uint256",
          "name": "depositAmount",
          "type": "uint256"
        },
        {
          "internalType": "uint256",
          "name": "premium",
          "type": "uint256"
        },
        {
          "internalType": "uint256",
          "name": "funding",
          "type": "uint256"
        },
        {
          "internalType": "uint256",
          "name": "underlying",
          "type": "uint256"
        }
      ],
      "stateMutability": "nonpayable",
      "type": "function"
    },
    {
      "inputs": [
        {
          "internalType": "uint256",
          "name": "maxStrikesCollateralIndex",
          "type": "uint256"
        },
        {
          "internalType": "uint256",
          "name": "epoch",
          "type": "uint256"
        },
        {
          "internalType": "address",
          "name": "user",
          "type": "address"
        }
      ],
      "name": "onRelockCollateral",
      "outputs": [
        {
          "internalType": "uint256",
          "name": "fundingCharged",
          "type": "uint256"
        },
        {
          "internalType": "uint256",
          "name": "prevFundingCharged",
          "type": "uint256"
        },
        {
          "components": [
            {
              "internalType": "address",
              "name": "user",
              "type": "address"
            },
            {
              "internalType": "uint256",
              "name": "optionStrike",
              "type": "uint256"
            },
            {
              "internalType": "uint256",
              "name": "optionsAmount",
              "type": "uint256"
            },
            {
              "internalType": "uint256",
              "name": "index",
              "type": "uint256"
            },
            {
              "components": [
                {
                  "internalType": "uint256",
                  "name": "fundingRate",
                  "type": "uint256"
                },
                {
                  "internalType": "uint256",
                  "name": "expiryDelta",
                  "type": "uint256"
                },
                {
                  "internalType": "uint256",
                  "name": "collateralAccess",
                  "type": "uint256"
                }
              ],
              "internalType": "struct CollateralUnlock",
              "name": "collateralUnlock",
              "type": "tuple"
            }
          ],
          "internalType": "struct MaxStrikesCollateral",
          "name": "_maxStrikeCollateral",
          "type": "tuple"
        }
      ],
      "stateMutability": "view",
      "type": "function"
    },
    {
      "inputs": [],
      "name": "putsPool",
      "outputs": [
        {
          "internalType": "contract IAtlanticPutsPool",
          "name": "",
          "type": "address"
        }
      ],
      "stateMutability": "view",
      "type": "function"
    },
    {
      "inputs": [
        {
          "internalType": "uint256",
          "name": "maxStrikesCollateralIndex",
          "type": "uint256"
        },
        {
          "internalType": "address",
          "name": "user",
          "type": "address"
        },
        {
          "internalType": "uint256",
          "name": "epoch",
          "type": "uint256"
        }
      ],
      "name": "relockCollateral",
      "outputs": [
        {
          "internalType": "uint256",
          "name": "unlockedCollateral",
          "type": "uint256"
        },
        {
          "internalType": "uint256",
          "name": "collateralToCollect",
          "type": "uint256"
        }
      ],
      "stateMutability": "nonpayable",
      "type": "function"
    },
    {
      "inputs": [
        {
          "internalType": "uint256",
          "name": "maxStrikesCollateralIndex",
          "type": "uint256"
        },
        {
          "internalType": "uint256",
          "name": "settlementPrice",
          "type": "uint256"
        },
        {
          "internalType": "address",
          "name": "user",
          "type": "address"
        },
        {
          "internalType": "uint256",
          "name": "epoch",
          "type": "uint256"
        }
      ],
      "name": "settle",
      "outputs": [
        {
          "internalType": "uint256",
          "name": "pnl",
          "type": "uint256"
        },
        {
          "internalType": "uint256",
          "name": "optionsAmount",
          "type": "uint256"
        }
      ],
      "stateMutability": "nonpayable",
      "type": "function"
    },
    {
      "inputs": [
        {
          "internalType": "uint256",
          "name": "epoch",
          "type": "uint256"
        },
        {
          "internalType": "uint256",
          "name": "putStrike",
          "type": "uint256"
        },
        {
          "internalType": "uint256",
          "name": "collateralRequired",
          "type": "uint256"
        },
        {
          "internalType": "uint256",
          "name": "amount",
          "type": "uint256"
        },
        {
          "internalType": "uint256",
          "name": "premium",
          "type": "uint256"
        },
        {
          "internalType": "address",
          "name": "user",
          "type": "address"
        }
      ],
      "name": "squeezeMaxStrikes",
      "outputs": [
        {
          "internalType": "uint256",
          "name": "maxStrikeCollateralIndex",
          "type": "uint256"
        }
      ],
      "stateMutability": "nonpayable",
      "type": "function"
    },
    {
      "inputs": [
        {
          "internalType": "uint256",
          "name": "maxStrikesCollateralIndex",
          "type": "uint256"
        },
        {
          "internalType": "uint256",
          "name": "epoch",
          "type": "uint256"
        },
        {
          "internalType": "address",
          "name": "user",
          "type": "address"
        },
        {
          "internalType": "address",
          "name": "to",
          "type": "address"
        }
      ],
      "name": "unlockCollateral",
      "outputs": [
        {
          "internalType": "uint256",
          "name": "unlockedCollateral",
          "type": "uint256"
        },
        {
          "internalType": "uint256",
          "name": "unlockedWithFee",
          "type": "uint256"
        }
      ],
      "stateMutability": "nonpayable",
      "type": "function"
    },
    {
      "inputs": [
        {
          "internalType": "uint256",
          "name": "maxStrikesCollateralIndex",
          "type": "uint256"
        },
        {
          "internalType": "address",
          "name": "user",
          "type": "address"
        },
        {
          "internalType": "uint256",
          "name": "epoch",
          "type": "uint256"
        }
      ],
      "name": "unwind",
      "outputs": [
        {
          "internalType": "uint256",
          "name": "unwindAmount",
          "type": "uint256"
        }
      ],
      "stateMutability": "nonpayable",
      "type": "function"
    },
    {
      "inputs": [
        {
          "internalType": "uint256",
          "name": "",
          "type": "uint256"
        },
        {
          "internalType": "address",
          "name": "",
          "type": "address"
        },
        {
          "internalType": "uint256",
          "name": "",
          "type": "uint256"
        }
      ],
      "name": "userMaxStrikesCollaterals",
      "outputs": [
        {
          "internalType": "uint256",
          "name": "",
          "type": "uint256"
        }
      ],
      "stateMutability": "view",
      "type": "function"
    }
  ]